{
	"problems":[
		{
			"avgPts":223.55,
			"constraints":[],
			"correctRatio":95.44,
			"definition":[],
			"div":0,
			"examples":[],
			"level":1,
			"link":"http://community.topcoder.com/stat?c=problem_statement&pm=3520&rd=6516",
			"name":"ClientsList",
			"notes":[],
			"submission":241
		},
		{
			"avgPts":375.1,
			"constraints":[],
			"correctRatio":46.37,
			"definition":[],
			"div":0,
			"examples":[],
			"level":2,
			"link":"http://community.topcoder.com/stat?c=problem_statement&pm=3518&rd=6516",
			"name":"TreeSpreading",
			"notes":[],
			"submission":179
		},
		{
			"avgPts":533.14,
			"constraints":[],
			"correctRatio":31.33,
			"definition":[],
			"div":0,
			"examples":[],
			"level":3,
			"link":"http://community.topcoder.com/stat?c=problem_statement&pm=3514&rd=6516",
			"name":"QuadrilateralSearch",
			"notes":[],
			"submission":83
		}
	],
	"name":"Single Round Match 227 > Round 1",
	"link":"http://community.topcoder.com/stat?c=round_overview&er=5&rd=6516"
}