{
	"problems":[
		{
			"avgPts":238.2,
			"constraints":[],
			"correctRatio":100,
			"definition":[],
			"div":0,
			"examples":[],
			"level":1,
			"link":"http://community.topcoder.com/stat?c=problem_statement&pm=137&rd=3021",
			"name":"ZBox",
			"notes":[],
			"submission":31
		},
		{
			"avgPts":462.17,
			"constraints":[],
			"correctRatio":93.55,
			"definition":[],
			"div":0,
			"examples":[],
			"level":2,
			"link":"http://community.topcoder.com/stat?c=problem_statement&pm=140&rd=3021",
			"name":"ThreeCentCoin",
			"notes":[],
			"submission":31
		},
		{
			"avgPts":749.24,
			"constraints":[],
			"correctRatio":86.21,
			"definition":[],
			"div":0,
			"examples":[],
			"level":3,
			"link":"http://community.topcoder.com/stat?c=problem_statement&pm=139&rd=3021",
			"name":"Spell",
			"notes":[],
			"submission":29
		}
	],
	"name":"Single Round Match 22 > Round 1",
	"link":"http://community.topcoder.com/stat?c=round_overview&er=5&rd=3021"
}