{
	"problems":[
		{
			"avgPts":186.78,
			"constraints":[],
			"correctRatio":63.67,
			"definition":[],
			"div":0,
			"examples":[],
			"level":1,
			"link":"http://community.topcoder.com/stat?c=problem_statement&pm=12350&rd=15187",
			"name":"MonstersValley",
			"notes":[],
			"submission":633
		},
		{
			"avgPts":278.91,
			"constraints":[],
			"correctRatio":67.63,
			"definition":[],
			"div":0,
			"examples":[],
			"level":2,
			"link":"http://community.topcoder.com/stat?c=problem_statement&pm=12264&rd=15187",
			"name":"TheDivisionGame",
			"notes":[],
			"submission":278
		},
		{
			"avgPts":400.58,
			"constraints":[],
			"correctRatio":66.67,
			"definition":[],
			"div":0,
			"examples":[],
			"level":3,
			"link":"http://community.topcoder.com/stat?c=problem_statement&pm=12353&rd=15187",
			"name":"UnknownTree",
			"notes":[],
			"submission":3
		}
	],
	"name":"Single Round Match 565 > Round 1",
	"link":"http://community.topcoder.com/stat?c=round_overview&er=5&rd=15187"
}