{
	"problems":[
		{
			"avgPts":254.73,
			"constraints":[],
			"correctRatio":81.92,
			"definition":[],
			"div":0,
			"examples":[],
			"level":1,
			"link":"http://community.topcoder.com/stat?c=problem_statement&pm=6431&rd=9991",
			"name":"MatrixTransforming",
			"notes":[],
			"submission":260
		},
		{
			"avgPts":374.31,
			"constraints":[],
			"correctRatio":84.21,
			"definition":[],
			"div":0,
			"examples":[],
			"level":2,
			"link":"http://community.topcoder.com/stat?c=problem_statement&pm=6430&rd=9991",
			"name":"SumThemAll",
			"notes":[],
			"submission":209
		},
		{
			"avgPts":507.77,
			"constraints":[],
			"correctRatio":35.94,
			"definition":[],
			"div":0,
			"examples":[],
			"level":3,
			"link":"http://community.topcoder.com/stat?c=problem_statement&pm=6591&rd=9991",
			"name":"MatchNumbersHard",
			"notes":[],
			"submission":64
		}
	],
	"name":"Single Round Match 311 > Round 1",
	"link":"http://community.topcoder.com/stat?c=round_overview&er=5&rd=9991"
}