{
	"problems":[
		{
			"avgPts":183.93,
			"constraints":[],
			"correctRatio":55.34,
			"definition":[],
			"div":0,
			"examples":[],
			"level":1,
			"link":"http://community.topcoder.com/stat?c=problem_statement&pm=3970&rd=7993",
			"name":"AutoLoan",
			"notes":[],
			"submission":262
		},
		{
			"avgPts":354.32,
			"constraints":[],
			"correctRatio":38.58,
			"definition":[],
			"div":0,
			"examples":[],
			"level":2,
			"link":"http://community.topcoder.com/stat?c=problem_statement&pm=4703&rd=7993",
			"name":"CompressionText",
			"notes":[],
			"submission":254
		},
		{
			"avgPts":521.16,
			"constraints":[],
			"correctRatio":64.71,
			"definition":[],
			"div":0,
			"examples":[],
			"level":3,
			"link":"http://community.topcoder.com/stat?c=problem_statement&pm=4701&rd=7993",
			"name":"ChutesAndLadders",
			"notes":[],
			"submission":34
		}
	],
	"name":"Single Round Match 258 > Round 1",
	"link":"http://community.topcoder.com/stat?c=round_overview&er=5&rd=7993"
}